mnemosynerpc/__init__.py
mnemosynerpc/session_pb2.py
mnemosynerpc/session_pb2_grpc.py
mnemosyne_client-0.18.4.dist-info/LICENSE.txt
mnemosyne_client-0.18.4.dist-info/METADATA
mnemosyne_client-0.18.4.dist-info/WHEEL
mnemosyne_client-0.18.4.dist-info/top_level.txt
mnemosyne_client-0.18.4.dist-info/RECORD
