Metadata-Version: 2.1
Name: mnemosyne-client
Version: 0.18.4
Summary: mnemosyne service grpc client library
Home-page: http://github.com/piotrkowalczuk/mnemosyne
Author: Piotr Kowalczuk
Author-email: p.kowalczuk.priv@gmail.com
License: MIT
Download-URL: https://github.com/piotrkowalczuk/mnemosyne/archive/v0.18.4.tar.gz
Keywords: mnemosyne,grpc,session,service,client
Platform: UNKNOWN
Requires-Dist: protobuf
Requires-Dist: grpcio
